ksc/__init__.py
ksc/__main__.py
ksc/macos.py
ksc-1.4.dist-info/licenses/LICENSE
ksc-1.4.dist-info/METADATA
ksc-1.4.dist-info/WHEEL
ksc-1.4.dist-info/entry_points.txt
ksc-1.4.dist-info/top_level.txt
ksc-1.4.dist-info/RECORD
