Metadata-Version: 2.4
Name: ksc
Version: 1.4
Summary: A command line tool and python library for documenting and describing keyboard shortcuts.
Author-email: Jared Crapo <jared@kotfu.net>
License-Expression: MIT
Project-URL: homepage, https://github.com/kotfu/ksc
Keywords: keyboard shortcut,documentation,command line
Classifier: Development Status :: 5 - Production/Stable
Classifier: Environment :: Console
Classifier: Operating System :: OS Independent
Classifier: Topic :: Utilities
Classifier: Topic :: Software Development :: Libraries :: Python Modules
Classifier: Intended Audience :: Developers
Classifier: Programming Language :: Python :: 3 :: Only
Classifier: Programming Language :: Python :: 3.10
Classifier: Programming Language :: Python :: 3.11
Classifier: Programming Language :: Python :: 3.12
Classifier: Programming Language :: Python :: 3.13
Classifier: Programming Language :: Python :: 3.14
Requires-Python: >=3.10
License-File: LICENSE
Requires-Dist: rich
Dynamic: license-file
